onnx_tool/__init__.py
onnx_tool/__main__.py
onnx_tool/fusion.py
onnx_tool/graph.py
onnx_tool/model.py
onnx_tool/node.py
onnx_tool/quantization.py
onnx_tool/serialization.py
onnx_tool/tensor.py
onnx_tool/utils.py
voe/__init__.py
voe/anchor_point.py
voe/graph.py
voe/model.py
voe/node.py
voe/pattern.py
voe/vis_pass.py
voe/generate_test_cases_pattern/__init__.py
voe/generate_test_cases_pattern/p50_dp_conv_relu_q.py
voe/generate_test_cases_pattern/p55_dp_conv_q.py
voe/passes/__init__.py
voe/passes/add_transpose_reshape_transpose_reshape.py
voe/passes/cal_coeff_utils.py
voe/passes/const_fold_batchnorm_to_scale.py
voe/passes/convert_fixneuron.py
voe/passes/convert_softmax_to_hard_softmax.py
voe/passes/convert_to_xir_op.py
voe/passes/convert_transpose_add_fix_input_fix_input.py
voe/passes/convert_transpose_fix_input.py
voe/passes/convert_transpose_fix_pad_fix_input.py
voe/passes/dynamic_dispatch.py
voe/passes/dynamic_dispatch_2.py
voe/passes/dynamic_dispatch_gen.py
voe/passes/dynamic_dispatch_gen_2.py
voe/passes/dynamic_dispatch_subgraphs.py
voe/passes/dynamic_dispatch_subgraphs_2.py
voe/passes/dynamic_dispatch_subgraphs_3.py
voe/passes/fuse.py
voe/passes/fuse_GEMM.py
voe/passes/fuse_GEMM_qdq.py
voe/passes/fuse_GMATMULINTEGER.py
voe/passes/fuse_MATMUL.py
voe/passes/fuse_MATMULINTEGER.py
voe/passes/fuse_MATMULNBITS.py
voe/passes/fuse_NMS.py
voe/passes/fuse_QDQ_MATMUL.py
voe/passes/fuse_QDQ_MATMUL_DYNAMIC.py
voe/passes/fuse_decode_filter_boxes.py
voe/passes/fuse_resize_norm.py
voe/passes/fuse_softmax.py
voe/passes/fuse_topk.py
voe/passes/graph_label_example.py
voe/passes/merge_mul.py
voe/passes/mzdk5_patterns.py
voe/passes/onnx_graph.py
voe/passes/onnx_graph_partitioner.py
voe/passes/op_fusion.py
voe/passes/op_fusion_index.py
voe/passes/partitioner.py
voe/passes/pattern_generate_rule.py
voe/passes/pss_pst_patterns.py
voe/passes/remove_fix_before_relu.py
voe/passes/remove_reshape_fix.py
voe/passes/try_fusion.py
voe/passes/tune_graph.py
voe/passes/utils.py
voe/passes/vaiml.py
voe-1.5.0.dev20250602211920.dist-info/licenses/LICENSE
voe-1.5.0.dev20250602211920.dist-info/licenses/LICENSE.txt
voe-1.5.0.dev20250602211920.dist-info/METADATA
voe-1.5.0.dev20250602211920.dist-info/WHEEL
voe-1.5.0.dev20250602211920.dist-info/entry_points.txt
voe-1.5.0.dev20250602211920.dist-info/top_level.txt
voe-1.5.0.dev20250602211920.dist-info/RECORD
