Metadata-Version: 2.4
Name: voe
Version: 1.5.0.dev20250602211920
Summary: some common util for vaip dev - Dummy
Author: help@amd.com
License: Copyright (C) 2023 – 2024 Advanced Micro Devices, Inc. All rights reserved.
License-File: LICENSE.txt
Dynamic: author
Dynamic: description
Dynamic: license
Dynamic: license-file
Dynamic: summary
Requires-Dist: onnxruntime-vitisai==1.22.0.dev20250602
